[
  {
    "name": "analysis",
    "display_name": "Проанализировать данные",
    "description": "Статистический анализ, корреляции, тренды и исследование данных",
    "is_active": true,
    "sort_order": 1
  },
  {
    "name": "transformation",
    "display_name": "Преобразовать данные",
    "description": "Очистка, нормализация и преобразование данных",
    "is_active": true,
    "sort_order": 2
  },
  {
    "name": "search",
    "display_name": "Искать и фильтровать данные",
    "description": "Поиск и фильтрация данных, содержащихся в заданном диапазоне",
    "is_active": true,
    "sort_order": 3
  },
  {
    "name": "generation",
    "display_name": "Создать синтетические данные",
    "description": "Создание синтетических данных для тестирования и разработки",
    "is_active": true,
    "sort_order": 4
  },
  {
    "name": "uncertain",
    "display_name": "Не относится к задачам, решаемым в электронных таблицах",
    "description": "Не относится ни к одной категории анализа, синтеза, поиска или обработки данных с помощью электронных таблиц",
    "is_active": false,
    "sort_order": 5
  }
]
